MANIFEST.in
README.md
setup.py
snortsig.py
snortsig_test.py
snortsig.egg-info/PKG-INFO
snortsig.egg-info/SOURCES.txt
snortsig.egg-info/dependency_links.txt
snortsig.egg-info/top_level.txt