Metadata-Version: 1.1
Name: snortsig
Version: 0.2
Summary: A module to simplify working with Snort signatures
Home-page: http://www.github.com/Phillipmartin/snortsig
Author: Philip Martin
Author-email: phillip.martin@gmail.com
License: MIT
Platform: UNKNOWN
Classifier: Development Status :: 4 - Beta
Classifier: Environment :: Console
Classifier: Intended Audience :: Developers
Classifier: Intended Audience :: System Administrators
Classifier: License :: OSI Approved :: MIT License
Classifier: Programming Language :: Python
Classifier: Topic :: Security
Classifier: Topic :: Software Development :: Libraries :: Python Modules
Requires: pyparsing
